config_template.py
weather_server.py
qweather_mcp_server-1.1.0.dist-info/licenses/LICENSE
qweather_mcp_server-1.1.0.dist-info/METADATA
qweather_mcp_server-1.1.0.dist-info/WHEEL
qweather_mcp_server-1.1.0.dist-info/entry_points.txt
qweather_mcp_server-1.1.0.dist-info/top_level.txt
qweather_mcp_server-1.1.0.dist-info/RECORD
