Metadata-Version: 2.4
Name: qweather-mcp-server
Version: 1.1.0
Summary: 中国天气查询 MCP 服务器
Home-page: https://github.com/modelcontextprotocol/weather-mcp-server
Author: MCP Weather Server
Author-email: 
License: MIT
Project-URL: Homepage, https://github.com/YOUR_USERNAME/qweather-mcp-server
Project-URL: Repository, https://github.com/YOUR_USERNAME/qweather-mcp-server
Classifier: Development Status :: 4 - Beta
Classifier: Intended Audience :: Developers
Classifier: License :: OSI Approved :: MIT License
Classifier: Programming Language :: Python :: 3
Classifier: Programming Language :: Python :: 3.8
Classifier: Programming Language :: Python :: 3.9
Classifier: Programming Language :: Python :: 3.10
Classifier: Programming Language :: Python :: 3.11
Classifier: Programming Language :: Python :: 3.12
Requires-Python: >=3.8
License-File: LICENSE
Requires-Dist: mcp>=1.0.0
Requires-Dist: httpx>=0.24.0
Requires-Dist: pyjwt[crypto]>=2.8.0
Requires-Dist: cryptography>=41.0.0
Dynamic: home-page
Dynamic: license-file
Dynamic: requires-python
